ichigo_whisper/__init__.py
ichigo_whisper/config/__init__.py
ichigo_whisper/config/trainer_config.py
ichigo_whisper/config/vq_config.py
ichigo_whisper/data/__init__.py
ichigo_whisper/data/dataset.py
ichigo_whisper/data/hf.py
ichigo_whisper/data/utils.py
ichigo_whisper/data/process_data/concat_dataset.py
ichigo_whisper/data/process_data/process_gigas.py
ichigo_whisper/data/process_data/process_gt.py
ichigo_whisper/data/process_data/split_data.py
ichigo_whisper/data/process_data/transcribe_dataset.py
ichigo_whisper/demo/__init__.py
ichigo_whisper/demo/app.py
ichigo_whisper/demo/inference.py
ichigo_whisper/demo/utils.py
ichigo_whisper/demo/samples/test.wav
ichigo_whisper/models/__init__.py
ichigo_whisper/models/factory.py
ichigo_whisper/models/layers.py
ichigo_whisper/models/modules.py
ichigo_whisper/models/vq_transformer.py
ichigo_whisper/scripts/concat_data.sh
ichigo_whisper/scripts/test.py
ichigo_whisper/scripts/test.sh
ichigo_whisper/scripts/train.py
ichigo_whisper/scripts/train_multi.sh
ichigo_whisper/scripts/train_single.sh
ichigo_whisper/trainer/__init__.py
ichigo_whisper/trainer/lightning_module.py
ichigo_whisper/trainer/trainer.py
ichigo_whisper/trainer/utils.py
ichigo_whisper/utils/data_eda.ipynb
ichigo_whisper/utils/token_viz.ipynb
ichigo_whisper/utils/data/libritts - merge 7lang - 512 last - p2 5e.csv
ichigo_whisper/utils/data/vivoice - merge 7lang - 512 last - p2 5e.csv
ichigo_whisper-2.3.0.dist-info/METADATA
ichigo_whisper-2.3.0.dist-info/WHEEL
ichigo_whisper-2.3.0.dist-info/top_level.txt
ichigo_whisper-2.3.0.dist-info/RECORD
