Metadata-Version: 2.2
Name: ichigo_whisper
Version: 2.3.0
Summary: Ichigo Whisper is a compact (22M parameters), open-source speech tokenizer for the whisper-medium model, designed to enhance performance on multilingual with minimal impact on its original English capabilities. Unlike models that output continuous embeddings, Ichigo Whisper compresses speech into discrete tokens, making it more compatible with large language models (LLMs) for immediate speech understanding.
Author-email: Charles <charles@jan.ai>
Requires-Python: >=3.10
Requires-Dist: datasets==3.1.0
Requires-Dist: huggingface_hub==0.26.2
Requires-Dist: lightning==2.4.0
Requires-Dist: openai_whisper==20240930
Requires-Dist: torch==2.5.1
Requires-Dist: torchaudio==2.5.1
Requires-Dist: vector_quantize_pytorch==1.6.22
Requires-Dist: webdataset==0.2.85
Requires-Dist: wandb>=0.12.10
Requires-Dist: librosa
Requires-Dist: soundfile
Requires-Dist: black
Requires-Dist: evaluate
Requires-Dist: transformers
Requires-Dist: jiwer
Requires-Dist: gradio
Requires-Dist: matplotlib
Requires-Dist: seaborn
Requires-Dist: build
Requires-Dist: twine
